synonym/__init__.py
synonym/synonym.py
synonym-0.1.3.dist-info/DESCRIPTION.rst
synonym-0.1.3.dist-info/METADATA
synonym-0.1.3.dist-info/RECORD
synonym-0.1.3.dist-info/WHEEL
synonym-0.1.3.dist-info/entry_points.txt
synonym-0.1.3.dist-info/metadata.json
synonym-0.1.3.dist-info/top_level.txt
