Metadata-Version: 2.0
Name: synonym
Version: 0.1.3
Summary: synonym: Instant synonym answers via command line.
Home-page: https://github.com/gavinzbq/synonym
Author: Shanyun Gao
Author-email: shanyun@g.clemson.edu
License: MIT license
Download-URL: https://github.com/gavinzbq/synonym/archive/0.1.3.tar.gz
Keywords: synonym
Platform: UNKNOWN
Classifier: Development Status :: 2 - Pre-Alpha
Classifier: Intended Audience :: Developers
Classifier: License :: OSI Approved :: MIT License
Classifier: Natural Language :: English
Classifier: Programming Language :: Python :: 2
Classifier: Programming Language :: Python :: 2.6
Classifier: Programming Language :: Python :: 2.7
Classifier: Programming Language :: Python :: 3
Classifier: Programming Language :: Python :: 3.3
Classifier: Programming Language :: Python :: 3.4
Classifier: Programming Language :: Python :: 3.5
Classifier: Programming Language :: Python :: 3.6
Classifier: Operating System :: Unix
Requires-Dist: crayons
Requires-Dist: pyquery
Requires-Dist: requests
Requires-Dist: requests-cache
